google_dork/__init__.py
google_dork/cli.py
google_dork/main.py
google_dork-1.1.1.dist-info/LICENSE
google_dork-1.1.1.dist-info/METADATA
google_dork-1.1.1.dist-info/WHEEL
google_dork-1.1.1.dist-info/entry_points.txt
google_dork-1.1.1.dist-info/top_level.txt
google_dork-1.1.1.dist-info/RECORD
