Metadata-Version: 2.1
Name: google_dork
Version: 1.1.1
Summary: Google Dorking CLI Tool without API
Author-email: bri-anadi & dword32bit <introboy333@gmail.com>
License: MIT
Project-URL: Homepage, https://github.com/dword32bit/google-dork
Project-URL: Bug Tracker, https://github.com/dword32bit/google-dork/issues
Keywords: google,dork,dorking,search,security,osint
Classifier: Development Status :: 5 - Production/Stable
Classifier: Intended Audience :: Developers
Classifier: License :: OSI Approved :: MIT License
Classifier: Programming Language :: Python :: 3
Classifier: Programming Language :: Python :: 3.6
Classifier: Programming Language :: Python :: 3.7
Classifier: Programming Language :: Python :: 3.8
Classifier: Programming Language :: Python :: 3.9
Requires-Python: >=3.6
License-File: LICENSE
Requires-Dist: requests>=2.32.3
Requires-Dist: beautifulsoup4>=4.12.3
